.DS_Store
LJW/HeroLJW.py
LJW/LJW.py
LJW/LJW_Upgrade.py
LJW/LJW_legacy.py
LJW/LJW_old.py
LJW/__init__.py
LJW-2.1.0.dist-info/LICENSE
LJW-2.1.0.dist-info/METADATA
LJW-2.1.0.dist-info/WHEEL
LJW-2.1.0.dist-info/top_level.txt
LJW-2.1.0.dist-info/RECORD
