Metadata-Version: 2.1
Name: LJW
Version: 2.1.0
Summary: All About LJW
Home-page: https://github.com/jaewoo4200/poem_LJW
Author: Jaewoo Lee
Author-email: doni04164@gmail.com
License: UNKNOWN
Platform: UNKNOWN
Classifier: Programming Language :: Python :: 3.0
Classifier: License :: OSI Approved :: MIT License
Classifier: Operating System :: OS Independent
Requires-Python: >=3.0
